pyswfaws/__init__.py
pyswfaws/activityworker.py
pyswfaws/datastores.py
pyswfaws/decisionworker.py
pyswfaws/decorators.py
pyswfaws/exceptions.py
pyswfaws/models.py
pyswfaws/promise.py
pyswfaws/serializers.py
pyswfaws/test.py
pyswfaws/util.py
PySwfAws-0.6.1.dist-info/DESCRIPTION.rst
PySwfAws-0.6.1.dist-info/METADATA
PySwfAws-0.6.1.dist-info/metadata.json
PySwfAws-0.6.1.dist-info/pbr.json
PySwfAws-0.6.1.dist-info/RECORD
PySwfAws-0.6.1.dist-info/top_level.txt
PySwfAws-0.6.1.dist-info/WHEEL
