Metadata-Version: 2.0
Name: PySwfAws
Version: 0.6.1
Summary: A framework for using the Amazon Simple Workflow service
Home-page: http://pyswf.readthedocs.org/en/latest/
Author: Brian Stempin
Author-email: brian.stempin@gmail.com
License: Apache 2.0
Keywords: aws swf simple workflow
Platform: UNKNOWN
Classifier: Development Status :: 3 - Alpha
Classifier: Intended Audience :: Developers
Classifier: License :: OSI Approved :: Apache Software License
Classifier: Programming Language :: Python :: 2.7
Requires-Dist: boto
Requires-Dist: cement
Requires-Dist: protobuf
Requires-Dist: nose
Requires-Dist: pytz
Requires-Dist: python-dateutil
Requires-Dist: venusian
